pyscore/__init__.py
pyscore/underscore.py
pyscore-0.0.1.dist-info/LICENSE
pyscore-0.0.1.dist-info/METADATA
pyscore-0.0.1.dist-info/WHEEL
pyscore-0.0.1.dist-info/top_level.txt
pyscore-0.0.1.dist-info/RECORD
