Metadata-Version: 2.1
Name: pyscore
Version: 0.0.1
Summary: Python implementation of Underscore JS
Home-page: https://github.com/pypa/sampleproject
Author: Kaushal28
Author-email: shah.kaushal95@gmail.com
License: UNKNOWN
Platform: UNKNOWN
Classifier: Programming Language :: Python :: 3
Classifier: License :: OSI Approved :: MIT License
Classifier: Operating System :: OS Independent
